eap_sdk/__init__.py
eap_sdk/blocks.py
eap_sdk/cli.py
eap_sdk/context.py
eap_sdk/contracts.py
eap_sdk/decorators.py
eap_sdk/errors.py
eap_sdk/plugins.py
eap_sdk/runtime.py
eap_sdk/telemetry.py
eap_sdk-0.1.1.dist-info/METADATA
eap_sdk-0.1.1.dist-info/WHEEL
eap_sdk-0.1.1.dist-info/entry_points.txt
eap_sdk-0.1.1.dist-info/RECORD
