Metadata-Version: 2.4
Name: eap-sdk
Version: 0.1.1
Summary: Domain-neutral orchestration SDK (flows/steps, local/remote, DI).
Author-email: Enterprise Assistant Platform <arman.avanesyan@yahoo.com>
Requires-Python: >=3.10
Requires-Dist: httpx<1.0,>=0.27
Requires-Dist: pydantic<3.0,>=2.8
Provides-Extra: dev
Requires-Dist: bandit>=1.7.9; extra == 'dev'
Requires-Dist: build>=1.0.0; extra == 'dev'
Requires-Dist: pyright>=1.1.386; extra == 'dev'
Requires-Dist: ruff>=0.6; extra == 'dev'
Requires-Dist: twine>=5.0.0; extra == 'dev'
Provides-Extra: observability
Requires-Dist: prometheus-client<1.0,>=0.20; extra == 'observability'
Provides-Extra: test
Requires-Dist: prometheus-client>=0.20; extra == 'test'
Requires-Dist: pytest-asyncio>=0.23; extra == 'test'
Requires-Dist: pytest-cov>=5; extra == 'test'
Requires-Dist: pytest>=8; extra == 'test'
